poiu/__about__.py
poiu/__init__.py
poiu/__main__.py
poiu/cli/__init__.py
poiu-0.0.1.dev9.dist-info/METADATA
poiu-0.0.1.dev9.dist-info/WHEEL
poiu-0.0.1.dev9.dist-info/entry_points.txt
poiu-0.0.1.dev9.dist-info/licenses/LICENSE.txt
poiu-0.0.1.dev9.dist-info/RECORD
