Metadata-Version: 2.4
Name: poiu
Version: 0.0.1.dev9
Project-URL: Documentation, https://github.com/André P. Santos/poiu#readme
Project-URL: Issues, https://github.com/André P. Santos/poiu/issues
Project-URL: Source, https://github.com/André P. Santos/poiu
Author-email: "André P. Santos" <andreztz@gmail.com>
License-Expression: MIT
License-File: LICENSE.txt
Classifier: Programming Language :: Python
Classifier: Programming Language :: Python :: 3.8
Classifier: Programming Language :: Python :: 3.9
Classifier: Programming Language :: Python :: 3.10
Classifier: Programming Language :: Python :: 3.11
Classifier: Programming Language :: Python :: 3.12
Requires-Python: >=3.8
Requires-Dist: click
